odoo/addons/backend_theme/__init__.py
odoo/addons/backend_theme/__manifest__.py
odoo/addons/backend_theme/images/screen.png
odoo/addons/backend_theme/static/description/icon.png
odoo/addons/backend_theme/static/description/img1.png
odoo/addons/backend_theme/static/description/img2.png
odoo/addons/backend_theme/static/description/img3.png
odoo/addons/backend_theme/static/description/img4.png
odoo/addons/backend_theme/static/description/img5.png
odoo/addons/backend_theme/static/description/index.html
odoo/addons/backend_theme/static/lib/css/drawer.3.2.0.css
odoo/addons/backend_theme/static/lib/js/drawer.3.2.0.js
odoo/addons/backend_theme/static/lib/js/iscroll-probe.5.2.0.js
odoo/addons/backend_theme/static/src/font/Roboto-Regular.ttf
odoo/addons/backend_theme/static/src/img/material-background.jpg
odoo/addons/backend_theme/static/src/js/web_responsive.js
odoo/addons/backend_theme/static/src/less/app_drawer.less
odoo/addons/backend_theme/static/src/less/main.less
odoo/addons/backend_theme/static/src/less/navbar.less
odoo/addons/backend_theme/static/src/less/variables.less
odoo/addons/backend_theme/static/src/less/bootswatch/bootswatch.less
odoo/addons/backend_theme/static/src/less/bootswatch/style.less
odoo/addons/backend_theme/static/src/less/bootswatch/variables.less
odoo/addons/backend_theme/views/assets.xml
odoo/addons/backend_theme/views/web.xml
odoo/addons/import_account_move/README.rst
odoo/addons/import_account_move/__init__.py
odoo/addons/import_account_move/__manifest__.py
odoo/addons/import_account_move/models/__init__.py
odoo/addons/import_account_move/models/account_move.py
odoo/addons/import_account_move/models/account_move_line.py
odoo/addons/import_account_move/models/aux_tables.py
odoo/addons/import_account_move/security/ir.model.access.csv
odoo/addons/import_account_move/static/description/icon.png
odoo/addons/import_account_move/template/import_move.csv
odoo/addons/import_account_move/template/import_move_line.csv
grupxarxa_customizations-1.0.dist-info/METADATA
grupxarxa_customizations-1.0.dist-info/WHEEL
grupxarxa_customizations-1.0.dist-info/RECORD
