Metadata-Version: 2.3
Name: grupxarxa-customizations
Version: 1.0
Requires-Python: >=3.8
Requires-Dist: odoo12-addon-account-payment-mode
Requires-Dist: odoo12-addon-l10n-es-partner
Requires-Dist: odoo12-addon-queue-job
Requires-Dist: odoo<12.1dev,>=12.0a
